copyright_tool/__init__.py
copyright_tool/cli.py
copyright_tool-0.4.0.dist-info/LICENSE
copyright_tool-0.4.0.dist-info/METADATA
copyright_tool-0.4.0.dist-info/WHEEL
copyright_tool-0.4.0.dist-info/entry_points.txt
copyright_tool-0.4.0.dist-info/top_level.txt
copyright_tool-0.4.0.dist-info/RECORD
