Metadata-Version: 2.1
Name: copyright-tool
Version: 0.4.0
Summary: Use to scan your git repo and add/update copyrights to files of various language types.
Home-page: https://github.com/stgraham2000@gmail.com/copyright_tool
Author: Steve Graham
Author-email: stgraham2000@gmail.com
License: MIT license
Keywords: copyright_tool
Platform: UNKNOWN
Classifier: Development Status :: 2 - Pre-Alpha
Classifier: Intended Audience :: Developers
Classifier: License :: OSI Approved :: MIT License
Classifier: Natural Language :: English
Classifier: Programming Language :: Python :: 2
Classifier: Programming Language :: Python :: 2.7
Classifier: Programming Language :: Python :: 3
Classifier: Programming Language :: Python :: 3.5
Classifier: Programming Language :: Python :: 3.6
Classifier: Programming Language :: Python :: 3.7
Classifier: Programming Language :: Python :: 3.8
Requires-Python: >=2.7, !=3.0.*, !=3.1.*, !=3.2.*, !=3.3.*, !=3.4.*
Requires-Dist: GitPython (>=3.1.11)
Requires-Dist: gitignore-parser (>=0.0.8)
